app/__init__.py
app/__init__.pyc
app/main.pyc
app/assets/screenshot-20250605-183118.png
app/assets/screenshot-20250605-183453.png
app/assets/screenshot-20250605-184012.png
syz_base-1.0.2.dist-info/METADATA
syz_base-1.0.2.dist-info/WHEEL
syz_base-1.0.2.dist-info/entry_points.txt
syz_base-1.0.2.dist-info/top_level.txt
syz_base-1.0.2.dist-info/zip-safe
syz_base-1.0.2.dist-info/RECORD
