Metadata-Version: 2.4
Name: syz_base
Version: 1.0.2
Requires-Python: >=3.8
Requires-Dist: PyQt6>=6.6.1
Requires-Dist: Pillow>=10.2.0
Dynamic: requires-dist
Dynamic: requires-python
